unmain.py
unmain-1.0.0.dist-info/LICENSE
unmain-1.0.0.dist-info/METADATA
unmain-1.0.0.dist-info/WHEEL
unmain-1.0.0.dist-info/top_level.txt
unmain-1.0.0.dist-info/RECORD
