Metadata-Version: 2.1
Name: unmain
Version: 1.0.0
Summary: The end to __name__ == __main__
Home-page: https://github.com/tmr232/unmain
Author: Tamir Bahar
Author-email: UNKNOWN
License: MIT
Platform: UNKNOWN
